{
  "timestamp": "2026-01-19T09:38:00.450363-03:00",
  "date": "19 de Janeiro de 2026",
  "time": "09:38",
  "fear_greed": {
    "value": 44,
    "classification": "Fear",
    "yesterday": 49,
    "week_ago": 26
  },
  "usdt_d": {
    "dominance": 5.777,
    "dominance_formatted": "5.777%",
    "ema_9": 5.78,
    "ema_21": 5.78,
    "ema_200": 6.17,
    "rsi": 32.31,
    "atr": 0.0003,
    "macd": 0.0,
    "sr_levels": {
      "resistance_w1": 6.74,
      "resistance_d1": 6.53,
      "resistance_h4": 6.17,
      "support_h4": 6.0,
      "support_w1": 5.86
    },
    "trend": "bearish",
    "crypto_impact": "BULLISH",
    "crypto_impact_class": "bullish",
    "impact_reason": "USDT.D abaixo da EMA 200 - dinheiro entrando em cripto (tendência de alta)",
    "next_level": "Suporte W1: 5.86%",
    "invalidation": "USDT.D voltar acima de 6.17% (EMA 200)",
    "below_ema_200": true,
    "below_ema_21": true,
    "below_ema_9": true
  },
  "analyses": {
    "BTC": {
      "symbol": "BTC",
      "price": 93122.0,
      "price_formatted": "$93,122.00",
      "price_change": -2.09004,
      "price_change_formatted": "-2.09%",
      "high_24h": 97778.1,
      "low_24h": 88465.9,
      "volume": 42644090757.0,
      "emas": {
        "price": 93122.0,
        "ema_9": 93912.19,
        "ema_21": 94446.8,
        "ema_200": 93133.0
      },
      "rsi": 27.28,
      "atr": 501.0,
      "macd": {
        "macd_line": -310.55,
        "signal_line": 54.08,
        "histogram": -364.63,
        "trend": "bearish_strong"
      },
      "structure": {
        "type": "bearish",
        "swing_highs": [
          95520.0,
          95544.0,
          95468.0
        ],
        "swing_lows": [
          95020.0,
          94869.0,
          92263.0
        ],
        "last_swing_high": 95468.0,
        "last_swing_low": 92263.0
      },
      "sr_levels": {
        "pdh": 95468.0,
        "pdl": 92263.0,
        "resistances": [
          94000,
          95468.0
        ],
        "supports": [
          93000,
          92263.0
        ]
      },
      "funding_rate": 0,
      "funding_formatted": "0.0000%",
      "open_interest": 0,
      "long_percent": 50.0,
      "short_percent": 50.0,
      "setups": {
        "long": {
          "type": "LONG",
          "style": "Moderado",
          "entry_low": 93093.0,
          "entry_high": 93465.0,
          "stop_loss": 92070.0,
          "target1": 94627.5,
          "target2": 95650.5,
          "rr1": "1.5:1",
          "rr2": "2.5:1",
          "trigger": "Rejeição com volume no suporte",
          "score": 4,
          "reasons": [
            "Preço próximo ao suporte $93,000",
            "RSI sobrevendido (27.28)",
            "Funding Rate baixo/negativo"
          ]
        },
        "short": {
          "type": "SHORT",
          "style": "Moderado",
          "entry_low": 93530.0,
          "entry_high": 93906.0,
          "stop_loss": 94940.0,
          "target1": 92355.0,
          "target2": 91321.0,
          "rr1": "1.5:1",
          "rr2": "2.5:1",
          "trigger": "Rejeição com volume na resistência",
          "score": 7,
          "reasons": [
            "Estrutura LH + LL confirmada",
            "Preço próximo à resistência $94,000",
            "Preço abaixo da EMA 200",
            "EMA 9 < EMA 21 (momentum bearish)"
          ]
        }
      },
      "bias": {
        "bias": "NEUTRO",
        "bias_class": "neutral",
        "bullish_factors": [
          "RSI sobrevendido (27.28)",
          "Funding Rate saudável"
        ],
        "bearish_factors": [
          "Estrutura de baixa (LH + LL)",
          "Preço abaixo da EMA 200",
          "EMA 9 < EMA 21"
        ]
      },
      "has_setup": true
    }
  }
}